unsplash_lite_dataset_api/__init__.py
unsplash_lite_dataset_api/cli.py
unsplash_lite_dataset_api/config.py
unsplash_lite_dataset_api/connection_timeout.py
unsplash_lite_dataset_api/documents.py
unsplash_lite_dataset_api/indexer.py
unsplash_lite_dataset_api/search.py
unsplash_lite_dataset_api/wordnet.py
unsplash_lite_dataset_api-0.1.1.dist-info/METADATA
unsplash_lite_dataset_api-0.1.1.dist-info/WHEEL
unsplash_lite_dataset_api-0.1.1.dist-info/entry_points.txt
unsplash_lite_dataset_api-0.1.1.dist-info/top_level.txt
unsplash_lite_dataset_api-0.1.1.dist-info/RECORD
