Metadata-Version: 2.4
Name: unsplash-lite-dataset-api
Version: 0.1.1
Summary: Utilities for building and querying an Unsplash-style OpenSearch index
Author: Baneet
Requires-Python: >=3.9
Requires-Dist: python-dotenv>=1.0
Requires-Dist: psycopg2-binary>=2.9
Requires-Dist: opensearch-py>=2.4
Requires-Dist: requests-aws4auth>=1.2
Requires-Dist: nltk>=3.8
Provides-Extra: dev
Requires-Dist: pytest>=7.4; extra == "dev"
